bangtex/__init__.py
bangtex/cli.py
bangtex/converter.py
bangtex-1.0.0.dist-info/METADATA
bangtex-1.0.0.dist-info/WHEEL
bangtex-1.0.0.dist-info/entry_points.txt
bangtex-1.0.0.dist-info/top_level.txt
bangtex-1.0.0.dist-info/RECORD
