Metadata-Version: 2.2
Name: bangtex
Version: 1.0.0
Summary: Unicode UTF-8 Bangla to Bangtex converter
Home-page: https://github.com/username/bangtex
Author: Rakib Mollah
Author-email: rakib1703115@gmail.com
Classifier: Programming Language :: Python :: 3
Classifier: License :: OSI Approved :: GNU General Public License v2 or later (GPLv2+)
Classifier: Operating System :: OS Independent
Requires-Python: >=3.6
Dynamic: author
Dynamic: author-email
Dynamic: classifier
Dynamic: description
Dynamic: description-content-type
Dynamic: home-page
Dynamic: requires-python
Dynamic: summary
